ipchecker/__init__.py
ipchecker/core.py
ipcuy-0.1.0.dist-info/licenses/LICENSE
ipcuy-0.1.0.dist-info/METADATA
ipcuy-0.1.0.dist-info/WHEEL
ipcuy-0.1.0.dist-info/top_level.txt
ipcuy-0.1.0.dist-info/RECORD
