Metadata-Version: 2.4
Name: IPCUY
Version: 0.1.0
Summary: Contoh package Python buatan sendiri
Home-page: https://github.com/fajarp/ipchecker_fajar
Author: Fajar P
Author-email: Nama Kamu <emailkamu@example.com>
License-Expression: MIT
Requires-Python: >=3.7
License-File: LICENSE
Dynamic: author
Dynamic: home-page
Dynamic: license-file
Dynamic: requires-python
